[
 {
  "subject": "ASTR",
  "number": "1",
  "title": "Stars and Black Holes",
  "units": "4.00",
  "restriction": "",
  "sections": [
   {
    "section_id": "",
    "group": "A",
    "type": "LE",
    "code": "A00",
    "days": "TuTh",
    "time_start": "9:30a",
    "time_end": "10:50a",
    "building": "Solis Hall",
    "room": "107",
    "instructor": "Shelley Wright",
    "avail": null,
    "limit": null,
    "waitlist": 0,
    "enrollable": 0,
    "cancelled": false,
    "note": ""
   },
   {
    "section_id": "151146",
    "group": "A",
    "type": "DI",
    "code": "A01",
    "days": "F",
    "time_start": "11:00a",
    "time_end": "11:50a",
    "building": "Solis Hall",
    "room": "107",
    "instructor": "Shelley Wright",
    "avail": 300,
    "limit": 300,
    "waitlist": 0,
    "enrollable": 1,
    "cancelled": false,
    "note": ""
   },
   {
    "section_id": "",
    "group": "A",
    "type": "FI",
    "code": "12/10/2026",
    "days": "",
    "time_start": "8:00a",
    "time_end": "10:59a",
    "building": "",
    "room": "",
    "instructor": "",
    "avail": null,
    "limit": null,
    "waitlist": 0,
    "enrollable": 0,
    "cancelled": 0,
    "note": ""
   }
  ]
 },
 {
  "subject": "ASTR",
  "number": "18",
  "title": "Additional Topics in Classical Physics",
  "units": "4.00",
  "restriction": "",
  "sections": [
   {
    "section_id": "",
    "group": "A",
    "type": "LE",
    "code": "A00",
    "days": "MWF",
    "time_start": "2:00p",
    "time_end": "2:50p",
    "building": "Coalition Building",
    "room": "124",
    "instructor": "Kam Arnold",
    "avail": null,
    "limit": null,
    "waitlist": 0,
    "enrollable": 0,
    "cancelled": false,
    "note": ""
   },
   {
    "section_id": "151147",
    "group": "A",
    "type": "DI",
    "code": "A01",
    "days": "Th",
    "time_start": "6:00p",
    "time_end": "6:50p",
    "building": "Warren Lecture Hall",
    "room": "2208",
    "instructor": "Kam Arnold",
    "avail": 37,
    "limit": 37,
    "waitlist": 0,
    "enrollable": 1,
    "cancelled": false,
    "note": ""
   },
   {
    "section_id": "",
    "group": "A",
    "type": "FI",
    "code": "12/09/2026",
    "days": "",
    "time_start": "3:00p",
    "time_end": "5:59p",
    "building": "",
    "room": "",
    "instructor": "",
    "avail": null,
    "limit": null,
    "waitlist": 0,
    "enrollable": 0,
    "cancelled": 0,
    "note": ""
   }
  ]
 },
 {
  "subject": "ASTR",
  "number": "20A",
  "title": "Introduction to Astrophysics I",
  "units": "4.00",
  "restriction": "",
  "sections": [
   {
    "section_id": "",
    "group": "A",
    "type": "LE",
    "code": "A00",
    "days": "TuTh",
    "time_start": "12:30p",
    "time_end": "1:50p",
    "building": "Cognitive Science Building",
    "room": "004",
    "instructor": "Christopher Theissen",
    "avail": null,
    "limit": null,
    "waitlist": 0,
    "enrollable": 0,
    "cancelled": false,
    "note": ""
   },
   {
    "section_id": "151148",
    "group": "A",
    "type": "DI",
    "code": "A01",
    "days": "W",
    "time_start": "6:00p",
    "time_end": "6:50p",
    "building": "Cognitive Science Building",
    "room": "004",
    "instructor": "Christopher Theissen",
    "avail": 56,
    "limit": 56,
    "waitlist": 0,
    "enrollable": 1,
    "cancelled": false,
    "note": ""
   },
   {
    "section_id": "",
    "group": "A",
    "type": "FI",
    "code": "12/11/2026",
    "days": "",
    "time_start": "11:30a",
    "time_end": "2:29p",
    "building": "",
    "room": "",
    "instructor": "",
    "avail": null,
    "limit": null,
    "waitlist": 0,
    "enrollable": 0,
    "cancelled": 0,
    "note": ""
   }
  ]
 },
 {
  "subject": "ASTR",
  "number": "65",
  "title": "The Astronomy of Climate Change",
  "units": "4.00",
  "restriction": "",
  "sections": [
   {
    "section_id": "",
    "group": "A",
    "type": "LE",
    "code": "A00",
    "days": "TuTh",
    "time_start": "2:00p",
    "time_end": "3:20p",
    "building": "Peterson Hall",
    "room": "104",
    "instructor": "Samantha Trumbo",
    "avail": null,
    "limit": null,
    "waitlist": 0,
    "enrollable": 0,
    "cancelled": false,
    "note": ""
   },
   {
    "section_id": "151149",
    "group": "A",
    "type": "DI",
    "code": "A01",
    "days": "W",
    "time_start": "5:00p",
    "time_end": "5:50p",
    "building": "Warren Lecture Hall",
    "room": "2204",
    "instructor": "Samantha Trumbo",
    "avail": 75,
    "limit": 75,
    "waitlist": 0,
    "enrollable": 1,
    "cancelled": false,
    "note": ""
   }
  ]
 },
 {
  "subject": "ASTR",
  "number": "101",
  "title": "Astrophysical Dynamics",
  "units": "4.00",
  "restriction": "",
  "sections": [
   {
    "section_id": "",
    "group": "A",
    "type": "LE",
    "code": "A00",
    "days": "MWF",
    "time_start": "11:00a",
    "time_end": "11:50a",
    "building": "Podemos",
    "room": "1A22",
    "instructor": "Adam Burgasser",
    "avail": null,
    "limit": null,
    "waitlist": 0,
    "enrollable": 0,
    "cancelled": false,
    "note": ""
   },
   {
    "section_id": "151150",
    "group": "A",
    "type": "DI",
    "code": "A01",
    "days": "Tu",
    "time_start": "6:00p",
    "time_end": "6:50p",
    "building": "Warren Lecture Hall",
    "room": "2208",
    "instructor": "Adam Burgasser",
    "avail": 40,
    "limit": 40,
    "waitlist": 0,
    "enrollable": 1,
    "cancelled": false,
    "note": ""
   },
   {
    "section_id": "",
    "group": "A",
    "type": "FI",
    "code": "12/08/2026",
    "days": "",
    "time_start": "11:30a",
    "time_end": "2:29p",
    "building": "",
    "room": "",
    "instructor": "",
    "avail": null,
    "limit": null,
    "waitlist": 0,
    "enrollable": 0,
    "cancelled": 0,
    "note": ""
   }
  ]
 },
 {
  "subject": "ASTR",
  "number": "104",
  "title": "Thermal Astrophysics",
  "units": "4.00",
  "restriction": "",
  "sections": [
   {
    "section_id": "",
    "group": "A",
    "type": "LE",
    "code": "A00",
    "days": "MWF",
    "time_start": "9:00a",
    "time_end": "9:50a",
    "building": "Center Hall",
    "room": "217B",
    "instructor": "Eve Lee",
    "avail": null,
    "limit": null,
    "waitlist": 0,
    "enrollable": 0,
    "cancelled": false,
    "note": ""
   },
   {
    "section_id": "151151",
    "group": "A",
    "type": "DI",
    "code": "A01",
    "days": "Th",
    "time_start": "6:00p",
    "time_end": "6:50p",
    "building": "Center Hall",
    "room": "203",
    "instructor": "Eve Lee",
    "avail": 32,
    "limit": 32,
    "waitlist": 0,
    "enrollable": 1,
    "cancelled": false,
    "note": ""
   },
   {
    "section_id": "",
    "group": "A",
    "type": "FI",
    "code": "12/09/2026",
    "days": "",
    "time_start": "8:00a",
    "time_end": "10:59a",
    "building": "",
    "room": "",
    "instructor": "",
    "avail": null,
    "limit": null,
    "waitlist": 0,
    "enrollable": 0,
    "cancelled": 0,
    "note": ""
   }
  ]
 },
 {
  "subject": "ASTR",
  "number": "122",
  "title": "Physical Cosmology",
  "units": "4.00",
  "restriction": "",
  "sections": [
   {
    "section_id": "",
    "group": "A",
    "type": "LE",
    "code": "A00",
    "days": "TuTh",
    "time_start": "11:00a",
    "time_end": "12:20p",
    "building": "Solis Hall",
    "room": "111",
    "instructor": "Ethan Nadler",
    "avail": null,
    "limit": null,
    "waitlist": 0,
    "enrollable": 0,
    "cancelled": false,
    "note": ""
   },
   {
    "section_id": "151152",
    "group": "A",
    "type": "DI",
    "code": "A01",
    "days": "W",
    "time_start": "6:00p",
    "time_end": "6:50p",
    "building": "Warren Lecture Hall",
    "room": "2114",
    "instructor": "Ethan Nadler",
    "avail": 37,
    "limit": 37,
    "waitlist": 0,
    "enrollable": 1,
    "cancelled": false,
    "note": ""
   },
   {
    "section_id": "",
    "group": "A",
    "type": "FI",
    "code": "12/09/2026",
    "days": "",
    "time_start": "11:30a",
    "time_end": "2:29p",
    "building": "",
    "room": "",
    "instructor": "",
    "avail": null,
    "limit": null,
    "waitlist": 0,
    "enrollable": 0,
    "cancelled": 0,
    "note": ""
   }
  ]
 },
 {
  "subject": "ASTR",
  "number": "150",
  "title": "Observational Optical Research Lab",
  "units": "5.00",
  "restriction": "",
  "sections": [
   {
    "section_id": "",
    "group": "A",
    "type": "LE",
    "code": "A00",
    "days": "TuTh",
    "time_start": "3:30p",
    "time_end": "4:50p",
    "building": "Solis Hall",
    "room": "109",
    "instructor": "Griffin Hosseinzadeh",
    "avail": null,
    "limit": null,
    "waitlist": 0,
    "enrollable": 0,
    "cancelled": false,
    "note": ""
   },
   {
    "section_id": "151153",
    "group": "A",
    "type": "LA",
    "code": "A50",
    "days": "F",
    "time_start": "4:00p",
    "time_end": "4:50p",
    "building": "Warren Lecture Hall",
    "room": "2114",
    "instructor": "Griffin Hosseinzadeh",
    "avail": 40,
    "limit": 40,
    "waitlist": 0,
    "enrollable": 1,
    "cancelled": false,
    "note": ""
   }
  ]
 },
 {
  "subject": "ASTR",
  "number": "200",
  "title": "Survey of Astronomy",
  "units": "4.00",
  "restriction": "",
  "sections": [
   {
    "section_id": "156238",
    "group": "A",
    "type": "LE",
    "code": "A00",
    "days": "MWF",
    "time_start": "10:00a",
    "time_end": "10:50a",
    "building": "Science and Engineering Research Facility",
    "room": "329",
    "instructor": "Karin Sandstrom",
    "avail": 30,
    "limit": 30,
    "waitlist": 0,
    "enrollable": 1,
    "cancelled": false,
    "note": ""
   }
  ]
 },
 {
  "subject": "ASTR",
  "number": "215",
  "title": "Stellar Remnants",
  "units": "4.00",
  "restriction": "",
  "sections": [
   {
    "section_id": "151154",
    "group": "A",
    "type": "LE",
    "code": "A00",
    "days": "MW",
    "time_start": "12:30p",
    "time_end": "1:50p",
    "building": "Science and Engineering Research Facility",
    "room": "329",
    "instructor": "Kyle Kremer",
    "avail": 30,
    "limit": 30,
    "waitlist": 0,
    "enrollable": 1,
    "cancelled": false,
    "note": ""
   }
  ]
 },
 {
  "subject": "ASTR",
  "number": "250",
  "title": "Astronomy & Astrophysics Colloquium",
  "units": "1.00 - 2.00",
  "restriction": "",
  "sections": [
   {
    "section_id": "151155",
    "group": "A",
    "type": "SE",
    "code": "A81",
    "days": "W",
    "time_start": "3:00p",
    "time_end": "3:50p",
    "building": "Science and Engineering Research Facility",
    "room": "383",
    "instructor": "",
    "avail": 30,
    "limit": 30,
    "waitlist": 0,
    "enrollable": 1,
    "cancelled": false,
    "note": ""
   }
  ]
 },
 {
  "subject": "ASTR",
  "number": "251",
  "title": "Astronomy & Astrophysics Journal Club",
  "units": "1.00 - 2.00",
  "restriction": "",
  "sections": [
   {
    "section_id": "151156",
    "group": "A",
    "type": "SE",
    "code": "A81",
    "days": "F",
    "time_start": "12:00p",
    "time_end": "12:50p",
    "building": "Science and Engineering Research Facility",
    "room": "383",
    "instructor": "",
    "avail": 30,
    "limit": 30,
    "waitlist": 0,
    "enrollable": 1,
    "cancelled": false,
    "note": ""
   }
  ]
 },
 {
  "subject": "ASTR",
  "number": "500",
  "title": "Astronomical Teaching Training",
  "units": "2.00",
  "restriction": "",
  "sections": [
   {
    "section_id": "151157",
    "group": "A",
    "type": "LE",
    "code": "A00",
    "days": "M",
    "time_start": "3:00p",
    "time_end": "4:50p",
    "building": "Science and Engineering Research Facility",
    "room": "329",
    "instructor": "Karin Sandstrom",
    "avail": 30,
    "limit": 30,
    "waitlist": 0,
    "enrollable": 1,
    "cancelled": false,
    "note": ""
   }
  ]
 }
]